thompson_sampling/__init__.py
thompson_sampling/bandit.py
thompson_sampling_example_unique-0.1.1.dist-info/METADATA
thompson_sampling_example_unique-0.1.1.dist-info/WHEEL
thompson_sampling_example_unique-0.1.1.dist-info/top_level.txt
thompson_sampling_example_unique-0.1.1.dist-info/RECORD
