Metadata-Version: 2.4
Name: thompson-sampling-example-unique
Version: 0.1.1
Summary: A simple implementation of Thompson Sampling for the Multi-Armed Bandit problem.
Requires-Python: >=3.6
Requires-Dist: numpy
Dynamic: requires-dist
Dynamic: requires-python
Dynamic: summary
